keycap/__init__.py
keycap/controller.py
keycap/keycap.py
keycap/main.py
keycap/plant.py
keycap/tests/__init__.py
keycap/tests/run_tests.py
keycap/tests/test_configuration.py
keycap/tests/test_controller.py
keycap/tests/test_plot.py
keycap/tests/test_write.py
keycap-1.0.1.dist-info/METADATA
keycap-1.0.1.dist-info/WHEEL
keycap-1.0.1.dist-info/top_level.txt
keycap-1.0.1.dist-info/RECORD
