Metadata-Version: 2.1
Name: keycap
Version: 1.0.1
Requires-Dist: contourpy >=1.1.1
Requires-Dist: cycler >=0.12.1
Requires-Dist: fonttools >=4.43.1
Requires-Dist: kiwisolver >=1.4.5
Requires-Dist: matplotlib >=3.8.0
Requires-Dist: numpy >=1.26.1
Requires-Dist: packaging >=23.2
Requires-Dist: Pillow >=10.1.0
Requires-Dist: pyparsing >=3.1.1
Requires-Dist: python-dateutil >=2.8.2
Requires-Dist: six >=1.16.0
